walmart_reviews-1.2.0.dev1.dist-info/DESCRIPTION.rst
walmart_reviews-1.2.0.dev1.dist-info/METADATA
walmart_reviews-1.2.0.dev1.dist-info/RECORD
walmart_reviews-1.2.0.dev1.dist-info/WHEEL
walmart_reviews-1.2.0.dev1.dist-info/metadata.json
walmart_reviews-1.2.0.dev1.dist-info/top_level.txt
wlmrt/__init__.py
wlmrt/review.py
