Metadata-Version: 2.0
Name: walmart-reviews
Version: 1.2.0.dev1
Summary: Parsing reviews from Walmart.com without using API
Home-page: https://github.com/jayrumi/walmart-reviews
Author: Yauheni Rumiantsau
Author-email: jrumyantsev@gmail.com
License: MIT License
Keywords: walmart parsing
Platform: UNKNOWN
Classifier: Intended Audience :: Developers
Classifier: Programming Language :: Python :: 3.5
Classifier: Programming Language :: Python :: 3.6
Requires: python (>= 3.5)
